prob_distrs
