Metadata-Version: 1.0
Name: prob-distrs
Version: 0.5.1
Summary: Some popular probability distributions
Home-page: https://github.com/AdityaVadlamani/prob-distrs
Author: Aditya Vadlamani
Author-email: aditya.t.vadlamani@gmail.com
License: UNKNOWN
Platform: UNKNOWN
